AUTHORS.rst
CONTRIBUTING.rst
HISTORY.rst
LICENSE
MANIFEST.in
README.rst
setup.cfg
setup.py
docs/Makefile
docs/authors.rst
docs/conf.py
docs/contributing.rst
docs/history.rst
docs/index.rst
docs/installation.rst
docs/make.bat
docs/readme.rst
docs/usage.rst
tests/__init__.py
tests/test_unique_id_gen.py
unique_id_gen/__init__.py
unique_id_gen/cli.py
unique_id_gen/unique_id_gen.py
unique_id_gen.egg-info/PKG-INFO
unique_id_gen.egg-info/SOURCES.txt
unique_id_gen.egg-info/dependency_links.txt
unique_id_gen.egg-info/entry_points.txt
unique_id_gen.egg-info/not-zip-safe
unique_id_gen.egg-info/requires.txt
unique_id_gen.egg-info/top_level.txt