Metadata-Version: 1.1
Name: unique-id-gen
Version: 0.1.0
Summary: A package that generates unique randomized ids
Home-page: https://github.com/mechasparrow/unique_id_gen
Author: Michael Navazhylau
Author-email: mikipux7@gmail.com
License: MIT license
Keywords: unique_id_gen
Platform: UNKNOWN
Classifier: Development Status :: 2 - Pre-Alpha
Classifier: Intended Audience :: Developers
Classifier: License :: OSI Approved :: MIT License
Classifier: Natural Language :: English
Classifier: Programming Language :: Python :: 2
Classifier: Programming Language :: Python :: 2.6
Classifier: Programming Language :: Python :: 2.7
Classifier: Programming Language :: Python :: 3
Classifier: Programming Language :: Python :: 3.3
Classifier: Programming Language :: Python :: 3.4
Classifier: Programming Language :: Python :: 3.5
